{
  "topGainers": [
    {
      "id": "agkphysics/wav2vec2-large-xlsr-53-amharic",
      "name": "wav2vec2-large-xlsr-53-amharic",
      "org": "agkphysics",
      "gain": 3969,
      "growth": 2,
      "start": 172334,
      "end": 176303
    },
    {
      "id": "rasyosef/roberta-base-amharic",
      "name": "roberta-base-amharic",
      "org": "rasyosef",
      "gain": 378,
      "growth": 184,
      "start": 205,
      "end": 583
    },
    {
      "id": "badrex/Ethio-ASR-tigrinya",
      "name": "Ethio-ASR-tigrinya",
      "org": "badrex",
      "gain": 148,
      "growth": 114,
      "start": 130,
      "end": 278
    },
    {
      "id": "rasyosef/gpt2-small-amharic",
      "name": "gpt2-small-amharic",
      "org": "rasyosef",
      "gain": 111,
      "growth": 144,
      "start": 77,
      "end": 188
    },
    {
      "id": "b1n1yam/shook-medium-amharic-2k",
      "name": "shook-medium-amharic-2k",
      "org": "b1n1yam",
      "gain": 106,
      "growth": 42,
      "start": 251,
      "end": 357
    },
    {
      "id": "rasyosef/bert-mini-amharic",
      "name": "bert-mini-amharic",
      "org": "rasyosef",
      "gain": 89,
      "growth": 33,
      "start": 270,
      "end": 359
    },
    {
      "id": "Davlan/bert-base-multilingual-cased-finetuned-amharic",
      "name": "bert-base-multilingual-cased-finetuned-amharic",
      "org": "Davlan",
      "gain": 76,
      "growth": 71,
      "start": 107,
      "end": 183
    },
    {
      "id": "lamekyemane09/tigrinya-human-model",
      "name": "tigrinya-human-model",
      "org": "lamekyemane09",
      "gain": 54,
      "growth": 6,
      "start": 852,
      "end": 906
    },
    {
      "id": "rasyosef/bert-tiny-amharic",
      "name": "bert-tiny-amharic",
      "org": "rasyosef",
      "gain": 51,
      "growth": 50,
      "start": 103,
      "end": 154
    },
    {
      "id": "luel/gemma-3-4b-tigrinya-qa",
      "name": "gemma-3-4b-tigrinya-qa",
      "org": "luel",
      "gain": 50,
      "growth": 47,
      "start": 107,
      "end": 157
    },
    {
      "id": "fgaim/tiroberta-geezswitch",
      "name": "tiroberta-geezswitch",
      "org": "fgaim",
      "gain": 48,
      "growth": 533,
      "start": 9,
      "end": 57
    },
    {
      "id": "fgaim/tielectra-geezswitch",
      "name": "tielectra-geezswitch",
      "org": "fgaim",
      "gain": 47,
      "growth": 671,
      "start": 7,
      "end": 54
    },
    {
      "id": "obann001/Ethiopia_sdxl_lora",
      "name": "Ethiopia_sdxl_lora",
      "org": "obann001",
      "gain": 10,
      "growth": 7,
      "start": 144,
      "end": 154
    },
    {
      "id": "luel/gemma-3-4b-tigrinya",
      "name": "gemma-3-4b-tigrinya",
      "org": "luel",
      "gain": 4,
      "growth": 57,
      "start": 7,
      "end": 11
    },
    {
      "id": "obann001/Ethiopia_Flux_LoRA",
      "name": "Ethiopia_Flux_LoRA",
      "org": "obann001",
      "gain": 4,
      "growth": 1,
      "start": 303,
      "end": 307
    },
    {
      "id": "Samuael/tigrinya-asr-characters",
      "name": "tigrinya-asr-characters",
      "org": "Samuael",
      "gain": 3,
      "growth": 30,
      "start": 10,
      "end": 13
    },
    {
      "id": "oddegen/wav2vec2-large-mms-1b-amharic-colab",
      "name": "wav2vec2-large-mms-1b-amharic-colab",
      "org": "oddegen",
      "gain": 2,
      "growth": 0,
      "start": 533,
      "end": 535
    },
    {
      "id": "abdukuzi/josie-4b-amharic-2026",
      "name": "josie-4b-amharic-2026",
      "org": "abdukuzi",
      "gain": 2,
      "growth": 2,
      "start": 85,
      "end": 87
    },
    {
      "id": "ey0syas/amharic-whisper-ai",
      "name": "amharic-whisper-ai",
      "org": "ey0syas",
      "gain": 2,
      "growth": 4,
      "start": 53,
      "end": 55
    },
    {
      "id": "zeharay/amharic-qa-demo-model",
      "name": "amharic-qa-demo-model",
      "org": "zeharay",
      "gain": 2,
      "growth": 5,
      "start": 43,
      "end": 45
    }
  ],
  "milestones": [
    {
      "id": "rasyosef/roberta-base-amharic",
      "milestone": 500,
      "downloads": 583,
      "date": "2026-06-30"
    },
    {
      "id": "rasyosef/gpt2-small-amharic",
      "milestone": 100,
      "downloads": 188,
      "date": "2026-06-30"
    }
  ]
}